{"loss": 1.1734468744488227, "val_loss": 0.911243824346198, "train_acc": 72.997988499548, "val_acc": 77.4138863206772, "timestamp": 1738867669, "checkpoint_dir_name": "checkpoint_000000", "should_checkpoint": true, "done": false, "training_iteration": 1, "trial_id": "e12c1511", "date": "2025-02-06_19-47-50", "time_this_iter_s": 1049.4389226436615, "time_total_s": 1049.4389226436615, "pid": 52726, "hostname": "jan-desktop", "node_ip": "10.7.0.4", "config": {"learning_rate": 0.0001329291894316216, "batch_size": 4, "weight_decay": 4.2079886696066345e-06, "auto_cast": true, "max_epochs": 100}, "time_since_restore": 1049.4389226436615, "iterations_since_restore": 1}
{"loss": 0.9171450884350472, "val_loss": 0.7628015256341961, "train_acc": 77.13048076923077, "val_acc": 80.02584658530571, "timestamp": 1738868696, "checkpoint_dir_name": "checkpoint_000001", "should_checkpoint": true, "done": false, "training_iteration": 2, "trial_id": "e12c1511", "date": "2025-02-06_20-04-56", "time_this_iter_s": 1026.8537194728851, "time_total_s": 2076.2926421165466, "pid": 52726, "hostname": "jan-desktop", "node_ip": "10.7.0.4", "config": {"learning_rate": 0.0001329291894316216, "batch_size": 4, "weight_decay": 4.2079886696066345e-06, "auto_cast": true, "max_epochs": 100}, "time_since_restore": 2076.2926421165466, "iterations_since_restore": 2}
{"loss": 0.8278206380166941, "val_loss": 0.742237253387769, "train_acc": 78.91899269600592, "val_acc": 80.63469479372124, "timestamp": 1738869722, "checkpoint_dir_name": "checkpoint_000002", "should_checkpoint": true, "done": false, "training_iteration": 3, "trial_id": "e12c1511", "date": "2025-02-06_20-22-03", "time_this_iter_s": 1026.148404598236, "time_total_s": 3102.4410467147827, "pid": 52726, "hostname": "jan-desktop", "node_ip": "10.7.0.4", "config": {"learning_rate": 0.0001329291894316216, "batch_size": 4, "weight_decay": 4.2079886696066345e-06, "auto_cast": true, "max_epochs": 100}, "time_since_restore": 3102.4410467147827, "iterations_since_restore": 3}
{"loss": 0.790104063173963, "val_loss": 0.6888137591878573, "train_acc": 79.71568203998191, "val_acc": 81.55355728139382, "timestamp": 1738870750, "checkpoint_dir_name": "checkpoint_000003", "should_checkpoint": true, "done": false, "training_iteration": 4, "trial_id": "e12c1511", "date": "2025-02-06_20-39-10", "time_this_iter_s": 1027.3891251087189, "time_total_s": 4129.830171823502, "pid": 52726, "hostname": "jan-desktop", "node_ip": "10.7.0.4", "config": {"learning_rate": 0.0001329291894316216, "batch_size": 4, "weight_decay": 4.2079886696066345e-06, "auto_cast": true, "max_epochs": 100}, "time_since_restore": 4129.830171823502, "iterations_since_restore": 4}
{"loss": 0.7482266509470841, "val_loss": 0.7348998944047425, "train_acc": 80.57045865692801, "val_acc": 80.6715364069691, "timestamp": 1738871777, "checkpoint_dir_name": "checkpoint_000004", "should_checkpoint": true, "done": false, "training_iteration": 5, "trial_id": "e12c1511", "date": "2025-02-06_20-56-17", "time_this_iter_s": 1026.956146478653, "time_total_s": 5156.7863183021545, "pid": 52726, "hostname": "jan-desktop", "node_ip": "10.7.0.4", "config": {"learning_rate": 0.0001329291894316216, "batch_size": 4, "weight_decay": 4.2079886696066345e-06, "auto_cast": true, "max_epochs": 100}, "time_since_restore": 5156.7863183021545, "iterations_since_restore": 5}
{"loss": 0.7249809599171082, "val_loss": 0.6898371201546656, "train_acc": 81.03987153805062, "val_acc": 81.8482168392505, "timestamp": 1738872802, "checkpoint_dir_name": "checkpoint_000005", "should_checkpoint": true, "done": false, "training_iteration": 6, "trial_id": "e12c1511", "date": "2025-02-06_21-13-22", "time_this_iter_s": 1025.1863474845886, "time_total_s": 6181.972665786743, "pid": 52726, "hostname": "jan-desktop", "node_ip": "10.7.0.4", "config": {"learning_rate": 0.0001329291894316216, "batch_size": 4, "weight_decay": 4.2079886696066345e-06, "auto_cast": true, "max_epochs": 100}, "time_since_restore": 6181.972665786743, "iterations_since_restore": 6}
{"loss": 0.701584350042459, "val_loss": 0.65646140827073, "train_acc": 81.57770106529422, "val_acc": 82.29998346071663, "timestamp": 1738873826, "checkpoint_dir_name": "checkpoint_000006", "should_checkpoint": true, "done": false, "training_iteration": 7, "trial_id": "e12c1511", "date": "2025-02-06_21-30-26", "time_this_iter_s": 1024.0816178321838, "time_total_s": 7206.054283618927, "pid": 52726, "hostname": "jan-desktop", "node_ip": "10.7.0.4", "config": {"learning_rate": 0.0001329291894316216, "batch_size": 4, "weight_decay": 4.2079886696066345e-06, "auto_cast": true, "max_epochs": 100}, "time_since_restore": 7206.054283618927, "iterations_since_restore": 7}
{"loss": 0.6861416024456007, "val_loss": 0.6440637446360455, "train_acc": 81.74310119267751, "val_acc": 82.78566917324129, "timestamp": 1738874850, "checkpoint_dir_name": "checkpoint_000007", "should_checkpoint": true, "done": false, "training_iteration": 8, "trial_id": "e12c1511", "date": "2025-02-06_21-47-30", "time_this_iter_s": 1024.000586271286, "time_total_s": 8230.054869890213, "pid": 52726, "hostname": "jan-desktop", "node_ip": "10.7.0.4", "config": {"learning_rate": 0.0001329291894316216, "batch_size": 4, "weight_decay": 4.2079886696066345e-06, "auto_cast": true, "max_epochs": 100}, "time_since_restore": 8230.054869890213, "iterations_since_restore": 8}
{"loss": 0.657454243298206, "val_loss": 0.599294046594037, "train_acc": 82.53144831730769, "val_acc": 83.53381502712031, "timestamp": 1738875874, "checkpoint_dir_name": "checkpoint_000008", "should_checkpoint": true, "done": false, "training_iteration": 9, "trial_id": "e12c1511", "date": "2025-02-06_22-04-35", "time_this_iter_s": 1024.279546737671, "time_total_s": 9254.334416627884, "pid": 52726, "hostname": "jan-desktop", "node_ip": "10.7.0.4", "config": {"learning_rate": 0.0001329291894316216, "batch_size": 4, "weight_decay": 4.2079886696066345e-06, "auto_cast": true, "max_epochs": 100}, "time_since_restore": 9254.334416627884, "iterations_since_restore": 9}
{"loss": 0.654650208790683, "val_loss": 0.6197710536089208, "train_acc": 82.54283214681952, "val_acc": 83.15755259697568, "timestamp": 1738876901, "checkpoint_dir_name": "checkpoint_000009", "should_checkpoint": true, "done": false, "training_iteration": 10, "trial_id": "e12c1511", "date": "2025-02-06_22-21-41", "time_this_iter_s": 1026.2137348651886, "time_total_s": 10280.548151493073, "pid": 52726, "hostname": "jan-desktop", "node_ip": "10.7.0.4", "config": {"learning_rate": 0.0001329291894316216, "batch_size": 4, "weight_decay": 4.2079886696066345e-06, "auto_cast": true, "max_epochs": 100}, "time_since_restore": 10280.548151493073, "iterations_since_restore": 10}
{"loss": 0.6388741748821404, "val_loss": 0.6050210254742867, "train_acc": 82.71587401380671, "val_acc": 83.58883516190006, "timestamp": 1738877928, "checkpoint_dir_name": "checkpoint_000010", "should_checkpoint": true, "done": false, "training_iteration": 11, "trial_id": "e12c1511", "date": "2025-02-06_22-38-48", "time_this_iter_s": 1027.2204866409302, "time_total_s": 11307.768638134003, "pid": 52726, "hostname": "jan-desktop", "node_ip": "10.7.0.4", "config": {"learning_rate": 0.0001329291894316216, "batch_size": 4, "weight_decay": 4.2079886696066345e-06, "auto_cast": true, "max_epochs": 100}, "time_since_restore": 11307.768638134003, "iterations_since_restore": 11}
{"loss": 0.6235968485733288, "val_loss": 0.5909275158825847, "train_acc": 83.04972995253945, "val_acc": 83.82149059007232, "timestamp": 1738878955, "checkpoint_dir_name": "checkpoint_000011", "should_checkpoint": true, "done": false, "training_iteration": 12, "trial_id": "e12c1511", "date": "2025-02-06_22-55-55", "time_this_iter_s": 1027.0317702293396, "time_total_s": 12334.800408363342, "pid": 52726, "hostname": "jan-desktop", "node_ip": "10.7.0.4", "config": {"learning_rate": 0.0001329291894316216, "batch_size": 4, "weight_decay": 4.2079886696066345e-06, "auto_cast": true, "max_epochs": 100}, "time_since_restore": 12334.800408363342, "iterations_since_restore": 12}
{"loss": 0.6137652454173399, "val_loss": 0.5931169976294041, "train_acc": 83.3396775353386, "val_acc": 83.75097407133465, "timestamp": 1738879981, "checkpoint_dir_name": "checkpoint_000012", "should_checkpoint": true, "done": false, "training_iteration": 13, "trial_id": "e12c1511", "date": "2025-02-06_23-13-02", "time_this_iter_s": 1026.3509600162506, "time_total_s": 13361.151368379593, "pid": 52726, "hostname": "jan-desktop", "node_ip": "10.7.0.4", "config": {"learning_rate": 0.0001329291894316216, "batch_size": 4, "weight_decay": 4.2079886696066345e-06, "auto_cast": true, "max_epochs": 100}, "time_since_restore": 13361.151368379593, "iterations_since_restore": 13}
{"loss": 0.6125747699663043, "val_loss": 0.5840204448749622, "train_acc": 83.43692561945267, "val_acc": 83.95859703731098, "timestamp": 1738881007, "checkpoint_dir_name": "checkpoint_000013", "should_checkpoint": true, "done": false, "training_iteration": 14, "trial_id": "e12c1511", "date": "2025-02-06_23-30-08", "time_this_iter_s": 1025.8277695178986, "time_total_s": 14386.979137897491, "pid": 52726, "hostname": "jan-desktop", "node_ip": "10.7.0.4", "config": {"learning_rate": 0.0001329291894316216, "batch_size": 4, "weight_decay": 4.2079886696066345e-06, "auto_cast": true, "max_epochs": 100}, "time_since_restore": 14386.979137897491, "iterations_since_restore": 14}
{"loss": 0.601936896511664, "val_loss": 0.5873778752444518, "train_acc": 83.66877152161408, "val_acc": 83.65073728221564, "timestamp": 1738882030, "checkpoint_dir_name": "checkpoint_000014", "should_checkpoint": true, "done": false, "training_iteration": 15, "trial_id": "e12c1511", "date": "2025-02-06_23-47-10", "time_this_iter_s": 1022.7436897754669, "time_total_s": 15409.722827672958, "pid": 52726, "hostname": "jan-desktop", "node_ip": "10.7.0.4", "config": {"learning_rate": 0.0001329291894316216, "batch_size": 4, "weight_decay": 4.2079886696066345e-06, "auto_cast": true, "max_epochs": 100}, "time_since_restore": 15409.722827672958, "iterations_since_restore": 15}
{"loss": 0.5861659441598588, "val_loss": 0.5918545666957895, "train_acc": 84.1225086035092, "val_acc": 83.71269117767916, "timestamp": 1738883057, "checkpoint_dir_name": "checkpoint_000015", "should_checkpoint": true, "done": false, "training_iteration": 16, "trial_id": "e12c1511", "date": "2025-02-07_00-04-17", "time_this_iter_s": 1026.74773645401, "time_total_s": 16436.47056412697, "pid": 52726, "hostname": "jan-desktop", "node_ip": "10.7.0.4", "config": {"learning_rate": 0.0001329291894316216, "batch_size": 4, "weight_decay": 4.2079886696066345e-06, "auto_cast": true, "max_epochs": 100}, "time_since_restore": 16436.47056412697, "iterations_since_restore": 16}
{"loss": 0.5817771936828892, "val_loss": 0.5712114732629723, "train_acc": 83.98581057897765, "val_acc": 84.19750719099277, "timestamp": 1738884087, "checkpoint_dir_name": "checkpoint_000016", "should_checkpoint": true, "done": false, "training_iteration": 17, "trial_id": "e12c1511", "date": "2025-02-07_00-21-28", "time_this_iter_s": 1030.7637259960175, "time_total_s": 17467.234290122986, "pid": 52726, "hostname": "jan-desktop", "node_ip": "10.7.0.4", "config": {"learning_rate": 0.0001329291894316216, "batch_size": 4, "weight_decay": 4.2079886696066345e-06, "auto_cast": true, "max_epochs": 100}, "time_since_restore": 17467.234290122986, "iterations_since_restore": 17}
{"loss": 0.5694696705353757, "val_loss": 0.5563675364893343, "train_acc": 84.39037398298817, "val_acc": 84.80423857659434, "timestamp": 1738885113, "checkpoint_dir_name": "checkpoint_000017", "should_checkpoint": true, "done": false, "training_iteration": 18, "trial_id": "e12c1511", "date": "2025-02-07_00-38-33", "time_this_iter_s": 1025.4271466732025, "time_total_s": 18492.66143679619, "pid": 52726, "hostname": "jan-desktop", "node_ip": "10.7.0.4", "config": {"learning_rate": 0.0001329291894316216, "batch_size": 4, "weight_decay": 4.2079886696066345e-06, "auto_cast": true, "max_epochs": 100}, "time_since_restore": 18492.66143679619, "iterations_since_restore": 18}
{"loss": 0.5619223633501679, "val_loss": 0.5594170189566082, "train_acc": 84.53942169008876, "val_acc": 84.49736748027614, "timestamp": 1738886137, "checkpoint_dir_name": "checkpoint_000018", "should_checkpoint": true, "done": false, "training_iteration": 19, "trial_id": "e12c1511", "date": "2025-02-07_00-55-38", "time_this_iter_s": 1024.210889339447, "time_total_s": 19516.872326135635, "pid": 52726, "hostname": "jan-desktop", "node_ip": "10.7.0.4", "config": {"learning_rate": 0.0001329291894316216, "batch_size": 4, "weight_decay": 4.2079886696066345e-06, "auto_cast": true, "max_epochs": 100}, "time_since_restore": 19516.872326135635, "iterations_since_restore": 19}
{"loss": 0.5621634930537807, "val_loss": 0.5599826859186093, "train_acc": 84.59387553418803, "val_acc": 84.3787780448718, "timestamp": 1738887160, "checkpoint_dir_name": "checkpoint_000019", "should_checkpoint": true, "done": false, "training_iteration": 20, "trial_id": "e12c1511", "date": "2025-02-07_01-12-40", "time_this_iter_s": 1022.4853384494781, "time_total_s": 20539.357664585114, "pid": 52726, "hostname": "jan-desktop", "node_ip": "10.7.0.4", "config": {"learning_rate": 0.0001329291894316216, "batch_size": 4, "weight_decay": 4.2079886696066345e-06, "auto_cast": true, "max_epochs": 100}, "time_since_restore": 20539.357664585114, "iterations_since_restore": 20}
{"loss": 0.5500816539757781, "val_loss": 0.5346586825946967, "train_acc": 84.79957639916174, "val_acc": 85.04561678172256, "timestamp": 1738888185, "checkpoint_dir_name": "checkpoint_000020", "should_checkpoint": true, "done": false, "training_iteration": 21, "trial_id": "e12c1511", "date": "2025-02-07_01-29-46", "time_this_iter_s": 1025.3357031345367, "time_total_s": 21564.69336771965, "pid": 52726, "hostname": "jan-desktop", "node_ip": "10.7.0.4", "config": {"learning_rate": 0.0001329291894316216, "batch_size": 4, "weight_decay": 4.2079886696066345e-06, "auto_cast": true, "max_epochs": 100}, "time_since_restore": 21564.69336771965, "iterations_since_restore": 21}
{"loss": 0.5520079199690372, "val_loss": 0.5431680197848214, "train_acc": 84.80516459668803, "val_acc": 85.10770288872452, "timestamp": 1738889214, "checkpoint_dir_name": "checkpoint_000021", "should_checkpoint": true, "done": false, "training_iteration": 22, "trial_id": "e12c1511", "date": "2025-02-07_01-46-55", "time_this_iter_s": 1028.8741717338562, "time_total_s": 22593.567539453506, "pid": 52726, "hostname": "jan-desktop", "node_ip": "10.7.0.4", "config": {"learning_rate": 0.0001329291894316216, "batch_size": 4, "weight_decay": 4.2079886696066345e-06, "auto_cast": true, "max_epochs": 100}, "time_since_restore": 22593.567539453506, "iterations_since_restore": 22}
{"loss": 0.5460078726636453, "val_loss": 0.5584714935844143, "train_acc": 84.95262024367193, "val_acc": 84.36563455374754, "timestamp": 1738890243, "checkpoint_dir_name": "checkpoint_000022", "should_checkpoint": true, "done": false, "training_iteration": 23, "trial_id": "e12c1511", "date": "2025-02-07_02-04-03", "time_this_iter_s": 1028.8482439517975, "time_total_s": 23622.415783405304, "pid": 52726, "hostname": "jan-desktop", "node_ip": "10.7.0.4", "config": {"learning_rate": 0.0001329291894316216, "batch_size": 4, "weight_decay": 4.2079886696066345e-06, "auto_cast": true, "max_epochs": 100}, "time_since_restore": 23622.415783405304, "iterations_since_restore": 23}
{"loss": 0.5434297965363496, "val_loss": 0.5330050037428736, "train_acc": 84.88177373541255, "val_acc": 84.95358512080868, "timestamp": 1738891267, "checkpoint_dir_name": "checkpoint_000023", "should_checkpoint": true, "done": false, "training_iteration": 24, "trial_id": "e12c1511", "date": "2025-02-07_02-21-08", "time_this_iter_s": 1024.1827478408813, "time_total_s": 24646.598531246185, "pid": 52726, "hostname": "jan-desktop", "node_ip": "10.7.0.4", "config": {"learning_rate": 0.0001329291894316216, "batch_size": 4, "weight_decay": 4.2079886696066345e-06, "auto_cast": true, "max_epochs": 100}, "time_since_restore": 24646.598531246185, "iterations_since_restore": 24}
{"loss": 0.5378411108213994, "val_loss": 0.5439360521857938, "train_acc": 85.07941095496383, "val_acc": 84.81371383957922, "timestamp": 1738892293, "checkpoint_dir_name": "checkpoint_000024", "should_checkpoint": true, "done": false, "training_iteration": 25, "trial_id": "e12c1511", "date": "2025-02-07_02-38-13", "time_this_iter_s": 1025.5436267852783, "time_total_s": 25672.142158031464, "pid": 52726, "hostname": "jan-desktop", "node_ip": "10.7.0.4", "config": {"learning_rate": 0.0001329291894316216, "batch_size": 4, "weight_decay": 4.2079886696066345e-06, "auto_cast": true, "max_epochs": 100}, "time_since_restore": 25672.142158031464, "iterations_since_restore": 25}
{"loss": 0.5329720939054258, "val_loss": 0.5287616120527188, "train_acc": 85.22183794070513, "val_acc": 85.23863093770545, "timestamp": 1738893315, "checkpoint_dir_name": "checkpoint_000025", "should_checkpoint": true, "done": false, "training_iteration": 26, "trial_id": "e12c1511", "date": "2025-02-07_02-55-15", "time_this_iter_s": 1021.8654253482819, "time_total_s": 26694.007583379745, "pid": 52726, "hostname": "jan-desktop", "node_ip": "10.7.0.4", "config": {"learning_rate": 0.0001329291894316216, "batch_size": 4, "weight_decay": 4.2079886696066345e-06, "auto_cast": true, "max_epochs": 100}, "time_since_restore": 26694.007583379745, "iterations_since_restore": 26}
{"loss": 0.5206905098212883, "val_loss": 0.5172177657567792, "train_acc": 85.35507496609961, "val_acc": 85.41425141765286, "timestamp": 1738894342, "checkpoint_dir_name": "checkpoint_000026", "should_checkpoint": true, "done": false, "training_iteration": 27, "trial_id": "e12c1511", "date": "2025-02-07_03-12-22", "time_this_iter_s": 1027.1076679229736, "time_total_s": 27721.11525130272, "pid": 52726, "hostname": "jan-desktop", "node_ip": "10.7.0.4", "config": {"learning_rate": 0.0001329291894316216, "batch_size": 4, "weight_decay": 4.2079886696066345e-06, "auto_cast": true, "max_epochs": 100}, "time_since_restore": 27721.11525130272, "iterations_since_restore": 27}
{"loss": 0.5178811514894995, "val_loss": 0.5243862290349272, "train_acc": 85.54584727872287, "val_acc": 85.21147446170282, "timestamp": 1738895368, "checkpoint_dir_name": "checkpoint_000027", "should_checkpoint": true, "done": false, "training_iteration": 28, "trial_id": "e12c1511", "date": "2025-02-07_03-29-28", "time_this_iter_s": 1025.611969947815, "time_total_s": 28746.727221250534, "pid": 52726, "hostname": "jan-desktop", "node_ip": "10.7.0.4", "config": {"learning_rate": 0.0001329291894316216, "batch_size": 4, "weight_decay": 4.2079886696066345e-06, "auto_cast": true, "max_epochs": 100}, "time_since_restore": 28746.727221250534, "iterations_since_restore": 28}
{"loss": 0.51736990487203, "val_loss": 0.5141543848647012, "train_acc": 85.54881366596811, "val_acc": 85.62979207758053, "timestamp": 1738896394, "checkpoint_dir_name": "checkpoint_000028", "should_checkpoint": true, "done": false, "training_iteration": 29, "trial_id": "e12c1511", "date": "2025-02-07_03-46-34", "time_this_iter_s": 1026.082927942276, "time_total_s": 29772.81014919281, "pid": 52726, "hostname": "jan-desktop", "node_ip": "10.7.0.4", "config": {"learning_rate": 0.0001329291894316216, "batch_size": 4, "weight_decay": 4.2079886696066345e-06, "auto_cast": true, "max_epochs": 100}, "time_since_restore": 29772.81014919281, "iterations_since_restore": 29}
{"loss": 0.5135937435883615, "val_loss": 0.5019827085195316, "train_acc": 85.74427098742603, "val_acc": 85.9307835100263, "timestamp": 1738897417, "checkpoint_dir_name": "checkpoint_000029", "should_checkpoint": true, "done": false, "training_iteration": 30, "trial_id": "e12c1511", "date": "2025-02-07_04-03-38", "time_this_iter_s": 1023.6702613830566, "time_total_s": 30796.480410575867, "pid": 52726, "hostname": "jan-desktop", "node_ip": "10.7.0.4", "config": {"learning_rate": 0.0001329291894316216, "batch_size": 4, "weight_decay": 4.2079886696066345e-06, "auto_cast": true, "max_epochs": 100}, "time_since_restore": 30796.480410575867, "iterations_since_restore": 30}
{"loss": 0.5132406490554826, "val_loss": 0.5158919016975495, "train_acc": 85.652849148381, "val_acc": 85.53989953155819, "timestamp": 1738898445, "checkpoint_dir_name": "checkpoint_000030", "should_checkpoint": true, "done": false, "training_iteration": 31, "trial_id": "e12c1511", "date": "2025-02-07_04-20-46", "time_this_iter_s": 1027.6206488609314, "time_total_s": 31824.101059436798, "pid": 52726, "hostname": "jan-desktop", "node_ip": "10.7.0.4", "config": {"learning_rate": 0.0001329291894316216, "batch_size": 4, "weight_decay": 4.2079886696066345e-06, "auto_cast": true, "max_epochs": 100}, "time_since_restore": 31824.101059436798, "iterations_since_restore": 31}
{"loss": 0.5095878307200554, "val_loss": 0.5108068127091974, "train_acc": 85.72330559664694, "val_acc": 85.56398278270875, "timestamp": 1738899472, "checkpoint_dir_name": "checkpoint_000031", "should_checkpoint": true, "done": false, "training_iteration": 32, "trial_id": "e12c1511", "date": "2025-02-07_04-37-52", "time_this_iter_s": 1026.8192451000214, "time_total_s": 32850.92030453682, "pid": 52726, "hostname": "jan-desktop", "node_ip": "10.7.0.4", "config": {"learning_rate": 0.0001329291894316216, "batch_size": 4, "weight_decay": 4.2079886696066345e-06, "auto_cast": true, "max_epochs": 100}, "time_since_restore": 32850.92030453682, "iterations_since_restore": 32}
{"loss": 0.4920165567845106, "val_loss": 0.51892395551006, "train_acc": 86.12545752691486, "val_acc": 85.4545128616042, "timestamp": 1738900500, "checkpoint_dir_name": "checkpoint_000032", "should_checkpoint": true, "done": false, "training_iteration": 33, "trial_id": "e12c1511", "date": "2025-02-07_04-55-00", "time_this_iter_s": 1027.443979024887, "time_total_s": 33878.36428356171, "pid": 52726, "hostname": "jan-desktop", "node_ip": "10.7.0.4", "config": {"learning_rate": 0.0001329291894316216, "batch_size": 4, "weight_decay": 4.2079886696066345e-06, "auto_cast": true, "max_epochs": 100}, "time_since_restore": 33878.36428356171, "iterations_since_restore": 33}
{"loss": 0.491578144710511, "val_loss": 0.5097393661489089, "train_acc": 86.16514412804077, "val_acc": 85.7519742357002, "timestamp": 1738901526, "checkpoint_dir_name": "checkpoint_000033", "should_checkpoint": true, "done": false, "training_iteration": 34, "trial_id": "e12c1511", "date": "2025-02-07_05-12-07", "time_this_iter_s": 1026.4682655334473, "time_total_s": 34904.832549095154, "pid": 52726, "hostname": "jan-desktop", "node_ip": "10.7.0.4", "config": {"learning_rate": 0.0001329291894316216, "batch_size": 4, "weight_decay": 4.2079886696066345e-06, "auto_cast": true, "max_epochs": 100}, "time_since_restore": 34904.832549095154, "iterations_since_restore": 34}
{"loss": 0.49412620620491604, "val_loss": 0.501544957715604, "train_acc": 86.1494520720332, "val_acc": 85.6756720496384, "timestamp": 1738902549, "checkpoint_dir_name": "checkpoint_000034", "should_checkpoint": true, "done": false, "training_iteration": 35, "trial_id": "e12c1511", "date": "2025-02-07_05-29-09", "time_this_iter_s": 1022.3828275203705, "time_total_s": 35927.215376615524, "pid": 52726, "hostname": "jan-desktop", "node_ip": "10.7.0.4", "config": {"learning_rate": 0.0001329291894316216, "batch_size": 4, "weight_decay": 4.2079886696066345e-06, "auto_cast": true, "max_epochs": 100}, "time_since_restore": 35927.215376615524, "iterations_since_restore": 35}
{"loss": 0.4880812888261345, "val_loss": 0.5140122737487157, "train_acc": 86.20628634019559, "val_acc": 85.64117192636424, "timestamp": 1738903573, "checkpoint_dir_name": "checkpoint_000035", "should_checkpoint": true, "done": false, "training_iteration": 36, "trial_id": "e12c1511", "date": "2025-02-07_05-46-14", "time_this_iter_s": 1024.5614304542542, "time_total_s": 36951.77680706978, "pid": 52726, "hostname": "jan-desktop", "node_ip": "10.7.0.4", "config": {"learning_rate": 0.0001329291894316216, "batch_size": 4, "weight_decay": 4.2079886696066345e-06, "auto_cast": true, "max_epochs": 100}, "time_since_restore": 36951.77680706978, "iterations_since_restore": 36}
{"loss": 0.48429995860904457, "val_loss": 0.4872412305863367, "train_acc": 86.26521239110782, "val_acc": 86.0416449909599, "timestamp": 1738904597, "checkpoint_dir_name": "checkpoint_000036", "should_checkpoint": true, "done": false, "training_iteration": 37, "trial_id": "e12c1511", "date": "2025-02-07_06-03-18", "time_this_iter_s": 1024.0427918434143, "time_total_s": 37975.81959891319, "pid": 52726, "hostname": "jan-desktop", "node_ip": "10.7.0.4", "config": {"learning_rate": 0.0001329291894316216, "batch_size": 4, "weight_decay": 4.2079886696066345e-06, "auto_cast": true, "max_epochs": 100}, "time_since_restore": 37975.81959891319, "iterations_since_restore": 37}
{"loss": 0.4779035135601751, "val_loss": 0.503895149073667, "train_acc": 86.43412675665681, "val_acc": 85.70285903599606, "timestamp": 1738905620, "checkpoint_dir_name": "checkpoint_000037", "should_checkpoint": true, "done": false, "training_iteration": 38, "trial_id": "e12c1511", "date": "2025-02-07_06-20-20", "time_this_iter_s": 1022.6309466362, "time_total_s": 38998.45054554939, "pid": 52726, "hostname": "jan-desktop", "node_ip": "10.7.0.4", "config": {"learning_rate": 0.0001329291894316216, "batch_size": 4, "weight_decay": 4.2079886696066345e-06, "auto_cast": true, "max_epochs": 100}, "time_since_restore": 38998.45054554939, "iterations_since_restore": 38}
{"loss": 0.4760256571157111, "val_loss": 0.4860840792581439, "train_acc": 86.51274670241618, "val_acc": 86.25129766600921, "timestamp": 1738906644, "checkpoint_dir_name": "checkpoint_000038", "should_checkpoint": true, "done": false, "training_iteration": 39, "trial_id": "e12c1511", "date": "2025-02-07_06-37-25", "time_this_iter_s": 1024.508236169815, "time_total_s": 40022.95878171921, "pid": 52726, "hostname": "jan-desktop", "node_ip": "10.7.0.4", "config": {"learning_rate": 0.0001329291894316216, "batch_size": 4, "weight_decay": 4.2079886696066345e-06, "auto_cast": true, "max_epochs": 100}, "time_since_restore": 40022.95878171921, "iterations_since_restore": 39}
{"loss": 0.47342447406715815, "val_loss": 0.4866223291716435, "train_acc": 86.52040069238987, "val_acc": 86.04871496959237, "timestamp": 1738907681, "checkpoint_dir_name": "checkpoint_000039", "should_checkpoint": true, "done": false, "training_iteration": 40, "trial_id": "e12c1511", "date": "2025-02-07_06-54-41", "time_this_iter_s": 1035.9127509593964, "time_total_s": 41058.871532678604, "pid": 52726, "hostname": "jan-desktop", "node_ip": "10.7.0.4", "config": {"learning_rate": 0.0001329291894316216, "batch_size": 4, "weight_decay": 4.2079886696066345e-06, "auto_cast": true, "max_epochs": 100}, "time_since_restore": 41058.871532678604, "iterations_since_restore": 40}
{"loss": 0.47603711121819087, "val_loss": 0.47770656556718877, "train_acc": 86.4872412013067, "val_acc": 86.37087730111769, "timestamp": 1738908713, "checkpoint_dir_name": "checkpoint_000040", "should_checkpoint": true, "done": false, "training_iteration": 41, "trial_id": "e12c1511", "date": "2025-02-07_07-11-54", "time_this_iter_s": 1032.6532504558563, "time_total_s": 42091.52478313446, "pid": 52726, "hostname": "jan-desktop", "node_ip": "10.7.0.4", "config": {"learning_rate": 0.0001329291894316216, "batch_size": 4, "weight_decay": 4.2079886696066345e-06, "auto_cast": true, "max_epochs": 100}, "time_since_restore": 42091.52478313446, "iterations_since_restore": 41}
{"loss": 0.47528520594661433, "val_loss": 0.48710849561004177, "train_acc": 86.5146178244165, "val_acc": 86.27875400641025, "timestamp": 1738909740, "checkpoint_dir_name": "checkpoint_000041", "should_checkpoint": true, "done": false, "training_iteration": 42, "trial_id": "e12c1511", "date": "2025-02-07_07-29-00", "time_this_iter_s": 1026.3272478580475, "time_total_s": 43117.85203099251, "pid": 52726, "hostname": "jan-desktop", "node_ip": "10.7.0.4", "config": {"learning_rate": 0.0001329291894316216, "batch_size": 4, "weight_decay": 4.2079886696066345e-06, "auto_cast": true, "max_epochs": 100}, "time_since_restore": 43117.85203099251, "iterations_since_restore": 42}
{"loss": 0.46993076896864094, "val_loss": 0.4936582900625136, "train_acc": 86.59649436534352, "val_acc": 86.1847142094017, "timestamp": 1738910918, "checkpoint_dir_name": "checkpoint_000042", "should_checkpoint": true, "done": false, "training_iteration": 43, "trial_id": "e12c1511", "date": "2025-02-07_07-48-38", "time_this_iter_s": 1178.0969998836517, "time_total_s": 44295.94903087616, "pid": 52726, "hostname": "jan-desktop", "node_ip": "10.7.0.4", "config": {"learning_rate": 0.0001329291894316216, "batch_size": 4, "weight_decay": 4.2079886696066345e-06, "auto_cast": true, "max_epochs": 100}, "time_since_restore": 44295.94903087616, "iterations_since_restore": 43}
{"loss": 0.4698834960742129, "val_loss": 0.47269622868340877, "train_acc": 86.63743797768738, "val_acc": 86.58550408859303, "timestamp": 1738911944, "checkpoint_dir_name": "checkpoint_000043", "should_checkpoint": true, "done": false, "training_iteration": 44, "trial_id": "e12c1511", "date": "2025-02-07_08-05-45", "time_this_iter_s": 1026.3365333080292, "time_total_s": 45322.28556418419, "pid": 52726, "hostname": "jan-desktop", "node_ip": "10.7.0.4", "config": {"learning_rate": 0.0001329291894316216, "batch_size": 4, "weight_decay": 4.2079886696066345e-06, "auto_cast": true, "max_epochs": 100}, "time_since_restore": 45322.28556418419, "iterations_since_restore": 44}
{"loss": 0.46958745345990693, "val_loss": 0.47881034921854737, "train_acc": 86.67357995870316, "val_acc": 86.53040505834977, "timestamp": 1738912973, "checkpoint_dir_name": "checkpoint_000044", "should_checkpoint": true, "done": false, "training_iteration": 45, "trial_id": "e12c1511", "date": "2025-02-07_08-22-53", "time_this_iter_s": 1028.4675192832947, "time_total_s": 46350.75308346748, "pid": 52726, "hostname": "jan-desktop", "node_ip": "10.7.0.4", "config": {"learning_rate": 0.0001329291894316216, "batch_size": 4, "weight_decay": 4.2079886696066345e-06, "auto_cast": true, "max_epochs": 100}, "time_since_restore": 46350.75308346748, "iterations_since_restore": 45}
{"loss": 0.4634995106307583, "val_loss": 0.4809924573451281, "train_acc": 86.80145424987673, "val_acc": 86.22345897024984, "timestamp": 1738914001, "checkpoint_dir_name": "checkpoint_000045", "should_checkpoint": true, "done": false, "training_iteration": 46, "trial_id": "e12c1511", "date": "2025-02-07_08-40-02", "time_this_iter_s": 1028.6095204353333, "time_total_s": 47379.36260390282, "pid": 52726, "hostname": "jan-desktop", "node_ip": "10.7.0.4", "config": {"learning_rate": 0.0001329291894316216, "batch_size": 4, "weight_decay": 4.2079886696066345e-06, "auto_cast": true, "max_epochs": 100}, "time_since_restore": 47379.36260390282, "iterations_since_restore": 46}
{"loss": 0.4715433832599471, "val_loss": 0.47869468081328603, "train_acc": 86.63658700073964, "val_acc": 86.37061924720578, "timestamp": 1738915028, "checkpoint_dir_name": "checkpoint_000046", "should_checkpoint": true, "done": false, "training_iteration": 47, "trial_id": "e12c1511", "date": "2025-02-07_08-57-08", "time_this_iter_s": 1026.317016839981, "time_total_s": 48405.6796207428, "pid": 52726, "hostname": "jan-desktop", "node_ip": "10.7.0.4", "config": {"learning_rate": 0.0001329291894316216, "batch_size": 4, "weight_decay": 4.2079886696066345e-06, "auto_cast": true, "max_epochs": 100}, "time_since_restore": 48405.6796207428, "iterations_since_restore": 47}
{"loss": 0.4573157049725867, "val_loss": 0.47603559633923903, "train_acc": 86.92910153681788, "val_acc": 86.40990744165023, "timestamp": 1738916052, "checkpoint_dir_name": "checkpoint_000047", "should_checkpoint": true, "done": false, "training_iteration": 48, "trial_id": "e12c1511", "date": "2025-02-07_09-14-13", "time_this_iter_s": 1024.6613864898682, "time_total_s": 49430.341007232666, "pid": 52726, "hostname": "jan-desktop", "node_ip": "10.7.0.4", "config": {"learning_rate": 0.0001329291894316216, "batch_size": 4, "weight_decay": 4.2079886696066345e-06, "auto_cast": true, "max_epochs": 100}, "time_since_restore": 49430.341007232666, "iterations_since_restore": 48}
{"loss": 0.46554375362685985, "val_loss": 0.46979087529497016, "train_acc": 86.7353728272929, "val_acc": 86.38048991206443, "timestamp": 1738917076, "checkpoint_dir_name": "checkpoint_000048", "should_checkpoint": true, "done": false, "training_iteration": 49, "trial_id": "e12c1511", "date": "2025-02-07_09-31-17", "time_this_iter_s": 1023.7150640487671, "time_total_s": 50454.05607128143, "pid": 52726, "hostname": "jan-desktop", "node_ip": "10.7.0.4", "config": {"learning_rate": 0.0001329291894316216, "batch_size": 4, "weight_decay": 4.2079886696066345e-06, "auto_cast": true, "max_epochs": 100}, "time_since_restore": 50454.05607128143, "iterations_since_restore": 49}
{"loss": 0.45491383992834017, "val_loss": 0.48384867306798696, "train_acc": 87.07154483070349, "val_acc": 86.28461538461538, "timestamp": 1738918102, "checkpoint_dir_name": "checkpoint_000049", "should_checkpoint": true, "done": false, "training_iteration": 50, "trial_id": "e12c1511", "date": "2025-02-07_09-48-22", "time_this_iter_s": 1025.1961433887482, "time_total_s": 51479.25221467018, "pid": 52726, "hostname": "jan-desktop", "node_ip": "10.7.0.4", "config": {"learning_rate": 0.0001329291894316216, "batch_size": 4, "weight_decay": 4.2079886696066345e-06, "auto_cast": true, "max_epochs": 100}, "time_since_restore": 51479.25221467018, "iterations_since_restore": 50}
{"loss": 0.4584763632388785, "val_loss": 0.4747678650998407, "train_acc": 86.94648321930474, "val_acc": 86.40205754848783, "timestamp": 1738919128, "checkpoint_dir_name": "checkpoint_000050", "should_checkpoint": true, "done": false, "training_iteration": 51, "trial_id": "e12c1511", "date": "2025-02-07_10-05-29", "time_this_iter_s": 1026.9714767932892, "time_total_s": 52506.22369146347, "pid": 52726, "hostname": "jan-desktop", "node_ip": "10.7.0.4", "config": {"learning_rate": 0.0001329291894316216, "batch_size": 4, "weight_decay": 4.2079886696066345e-06, "auto_cast": true, "max_epochs": 100}, "time_since_restore": 52506.22369146347, "iterations_since_restore": 51}
{"loss": 0.4572211629395477, "val_loss": 0.4700525690325432, "train_acc": 86.94718426405325, "val_acc": 86.504545734714, "timestamp": 1738920158, "checkpoint_dir_name": "checkpoint_000051", "should_checkpoint": true, "done": false, "training_iteration": 52, "trial_id": "e12c1511", "date": "2025-02-07_10-22-38", "time_this_iter_s": 1029.393500328064, "time_total_s": 53535.617191791534, "pid": 52726, "hostname": "jan-desktop", "node_ip": "10.7.0.4", "config": {"learning_rate": 0.0001329291894316216, "batch_size": 4, "weight_decay": 4.2079886696066345e-06, "auto_cast": true, "max_epochs": 100}, "time_since_restore": 53535.617191791534, "iterations_since_restore": 52}
{"loss": 0.4527693245239142, "val_loss": 0.46432710291610824, "train_acc": 87.09611807096482, "val_acc": 86.86017915844839, "timestamp": 1738921186, "checkpoint_dir_name": "checkpoint_000052", "should_checkpoint": true, "done": false, "training_iteration": 53, "trial_id": "e12c1511", "date": "2025-02-07_10-39-46", "time_this_iter_s": 1027.6142938137054, "time_total_s": 54563.23148560524, "pid": 52726, "hostname": "jan-desktop", "node_ip": "10.7.0.4", "config": {"learning_rate": 0.0001329291894316216, "batch_size": 4, "weight_decay": 4.2079886696066345e-06, "auto_cast": true, "max_epochs": 100}, "time_since_restore": 54563.23148560524, "iterations_since_restore": 53}
{"loss": 0.46022622217941617, "val_loss": 0.46462038801982997, "train_acc": 86.8651370911407, "val_acc": 86.76340894148586, "timestamp": 1738922213, "checkpoint_dir_name": "checkpoint_000053", "should_checkpoint": true, "done": false, "training_iteration": 54, "trial_id": "e12c1511", "date": "2025-02-07_10-56-54", "time_this_iter_s": 1027.4824628829956, "time_total_s": 55590.713948488235, "pid": 52726, "hostname": "jan-desktop", "node_ip": "10.7.0.4", "config": {"learning_rate": 0.0001329291894316216, "batch_size": 4, "weight_decay": 4.2079886696066345e-06, "auto_cast": true, "max_epochs": 100}, "time_since_restore": 55590.713948488235, "iterations_since_restore": 54}
{"loss": 0.45484036396723243, "val_loss": 0.4788418051921245, "train_acc": 86.9860828864645, "val_acc": 86.44318026791585, "timestamp": 1738923239, "checkpoint_dir_name": "checkpoint_000054", "should_checkpoint": true, "done": false, "training_iteration": 55, "trial_id": "e12c1511", "date": "2025-02-07_11-14-00", "time_this_iter_s": 1026.1352770328522, "time_total_s": 56616.84922552109, "pid": 52726, "hostname": "jan-desktop", "node_ip": "10.7.0.4", "config": {"learning_rate": 0.0001329291894316216, "batch_size": 4, "weight_decay": 4.2079886696066345e-06, "auto_cast": true, "max_epochs": 100}, "time_since_restore": 56616.84922552109, "iterations_since_restore": 55}
{"loss": 0.44967030285547177, "val_loss": 0.47087538050280675, "train_acc": 87.18472170857989, "val_acc": 86.57278363330046, "timestamp": 1738924269, "checkpoint_dir_name": "checkpoint_000055", "should_checkpoint": true, "done": false, "training_iteration": 56, "trial_id": "e12c1511", "date": "2025-02-07_11-31-09", "time_this_iter_s": 1029.453625679016, "time_total_s": 57646.302851200104, "pid": 52726, "hostname": "jan-desktop", "node_ip": "10.7.0.4", "config": {"learning_rate": 0.0001329291894316216, "batch_size": 4, "weight_decay": 4.2079886696066345e-06, "auto_cast": true, "max_epochs": 100}, "time_since_restore": 57646.302851200104, "iterations_since_restore": 56}
{"loss": 0.4451501842037154, "val_loss": 0.4673565668830027, "train_acc": 87.24973390758547, "val_acc": 86.52501992932281, "timestamp": 1738925299, "checkpoint_dir_name": "checkpoint_000056", "should_checkpoint": true, "done": false, "training_iteration": 57, "trial_id": "e12c1511", "date": "2025-02-07_11-48-19", "time_this_iter_s": 1029.8716142177582, "time_total_s": 58676.17446541786, "pid": 52726, "hostname": "jan-desktop", "node_ip": "10.7.0.4", "config": {"learning_rate": 0.0001329291894316216, "batch_size": 4, "weight_decay": 4.2079886696066345e-06, "auto_cast": true, "max_epochs": 100}, "time_since_restore": 58676.17446541786, "iterations_since_restore": 57}
{"loss": 0.44564566411181455, "val_loss": 0.4568593024214109, "train_acc": 87.1717179795365, "val_acc": 87.03331843770546, "timestamp": 1738926326, "checkpoint_dir_name": "checkpoint_000057", "should_checkpoint": true, "done": false, "training_iteration": 58, "trial_id": "e12c1511", "date": "2025-02-07_12-05-27", "time_this_iter_s": 1027.5324230194092, "time_total_s": 59703.70688843727, "pid": 52726, "hostname": "jan-desktop", "node_ip": "10.7.0.4", "config": {"learning_rate": 0.0001329291894316216, "batch_size": 4, "weight_decay": 4.2079886696066345e-06, "auto_cast": true, "max_epochs": 100}, "time_since_restore": 59703.70688843727, "iterations_since_restore": 58}
{"loss": 0.4429114963693751, "val_loss": 0.4656112950709131, "train_acc": 87.29051721215484, "val_acc": 86.52189708662064, "timestamp": 1738927355, "checkpoint_dir_name": "checkpoint_000058", "should_checkpoint": true, "done": false, "training_iteration": 59, "trial_id": "e12c1511", "date": "2025-02-07_12-22-36", "time_this_iter_s": 1028.5634908676147, "time_total_s": 60732.270379304886, "pid": 52726, "hostname": "jan-desktop", "node_ip": "10.7.0.4", "config": {"learning_rate": 0.0001329291894316216, "batch_size": 4, "weight_decay": 4.2079886696066345e-06, "auto_cast": true, "max_epochs": 100}, "time_since_restore": 60732.270379304886, "iterations_since_restore": 59}
{"loss": 0.44635306808114467, "val_loss": 0.4700017407619291, "train_acc": 87.23062345907297, "val_acc": 86.56140666091387, "timestamp": 1738928382, "checkpoint_dir_name": "checkpoint_000059", "should_checkpoint": true, "done": false, "training_iteration": 60, "trial_id": "e12c1511", "date": "2025-02-07_12-39-42", "time_this_iter_s": 1026.8207261562347, "time_total_s": 61759.09110546112, "pid": 52726, "hostname": "jan-desktop", "node_ip": "10.7.0.4", "config": {"learning_rate": 0.0001329291894316216, "batch_size": 4, "weight_decay": 4.2079886696066345e-06, "auto_cast": true, "max_epochs": 100}, "time_since_restore": 61759.09110546112, "iterations_since_restore": 60}
{"loss": 0.4372279951403228, "val_loss": 0.46930745693544546, "train_acc": 87.45163117398093, "val_acc": 86.69864018326759, "timestamp": 1738929410, "checkpoint_dir_name": "checkpoint_000060", "should_checkpoint": true, "done": false, "training_iteration": 61, "trial_id": "e12c1511", "date": "2025-02-07_12-56-51", "time_this_iter_s": 1028.069823026657, "time_total_s": 62787.16092848778, "pid": 52726, "hostname": "jan-desktop", "node_ip": "10.7.0.4", "config": {"learning_rate": 0.0001329291894316216, "batch_size": 4, "weight_decay": 4.2079886696066345e-06, "auto_cast": true, "max_epochs": 100}, "time_since_restore": 62787.16092848778, "iterations_since_restore": 61}
{"loss": 0.44631900729508034, "val_loss": 0.4646844397692217, "train_acc": 87.19020114234057, "val_acc": 86.6429307404668, "timestamp": 1738930441, "checkpoint_dir_name": "checkpoint_000061", "should_checkpoint": true, "done": false, "training_iteration": 62, "trial_id": "e12c1511", "date": "2025-02-07_13-14-02", "time_this_iter_s": 1031.2777616977692, "time_total_s": 63818.43869018555, "pid": 52726, "hostname": "jan-desktop", "node_ip": "10.7.0.4", "config": {"learning_rate": 0.0001329291894316216, "batch_size": 4, "weight_decay": 4.2079886696066345e-06, "auto_cast": true, "max_epochs": 100}, "time_since_restore": 63818.43869018555, "iterations_since_restore": 62}
{"loss": 0.4427687436256868, "val_loss": 0.4642753042860164, "train_acc": 87.26093541974852, "val_acc": 86.77214096400394, "timestamp": 1738931471, "checkpoint_dir_name": "checkpoint_000062", "should_checkpoint": true, "done": false, "training_iteration": 63, "trial_id": "e12c1511", "date": "2025-02-07_13-31-12", "time_this_iter_s": 1029.9701948165894, "time_total_s": 64848.408885002136, "pid": 52726, "hostname": "jan-desktop", "node_ip": "10.7.0.4", "config": {"learning_rate": 0.0001329291894316216, "batch_size": 4, "weight_decay": 4.2079886696066345e-06, "auto_cast": true, "max_epochs": 100}, "time_since_restore": 64848.408885002136, "iterations_since_restore": 63}
{"loss": 0.4409905761718336, "val_loss": 0.4601242698356509, "train_acc": 87.3393911283695, "val_acc": 86.87569783448389, "timestamp": 1738932499, "checkpoint_dir_name": "checkpoint_000063", "should_checkpoint": true, "done": false, "training_iteration": 64, "trial_id": "e12c1511", "date": "2025-02-07_13-48-20", "time_this_iter_s": 1027.5969352722168, "time_total_s": 65876.00582027435, "pid": 52726, "hostname": "jan-desktop", "node_ip": "10.7.0.4", "config": {"learning_rate": 0.0001329291894316216, "batch_size": 4, "weight_decay": 4.2079886696066345e-06, "auto_cast": true, "max_epochs": 100}, "time_since_restore": 65876.00582027435, "iterations_since_restore": 64}
{"loss": 0.4391084180265251, "val_loss": 0.4814804989989433, "train_acc": 87.35820743959566, "val_acc": 86.41143480851413, "timestamp": 1738933529, "checkpoint_dir_name": "checkpoint_000064", "should_checkpoint": true, "done": false, "training_iteration": 65, "trial_id": "e12c1511", "date": "2025-02-07_14-05-29", "time_this_iter_s": 1029.2635743618011, "time_total_s": 66905.26939463615, "pid": 52726, "hostname": "jan-desktop", "node_ip": "10.7.0.4", "config": {"learning_rate": 0.0001329291894316216, "batch_size": 4, "weight_decay": 4.2079886696066345e-06, "auto_cast": true, "max_epochs": 100}, "time_since_restore": 66905.26939463615, "iterations_since_restore": 65}
{"loss": 0.44016894191193084, "val_loss": 0.45690195822053487, "train_acc": 87.33964129787147, "val_acc": 86.76136320677186, "timestamp": 1738934556, "checkpoint_dir_name": "checkpoint_000065", "should_checkpoint": true, "done": false, "training_iteration": 66, "trial_id": "e12c1511", "date": "2025-02-07_14-22-37", "time_this_iter_s": 1027.6202764511108, "time_total_s": 67932.88967108727, "pid": 52726, "hostname": "jan-desktop", "node_ip": "10.7.0.4", "config": {"learning_rate": 0.0001329291894316216, "batch_size": 4, "weight_decay": 4.2079886696066345e-06, "auto_cast": true, "max_epochs": 100}, "time_since_restore": 67932.88967108727, "iterations_since_restore": 66}
{"loss": 0.43787297724125285, "val_loss": 0.4508265581313107, "train_acc": 87.42708202354537, "val_acc": 86.83087668474688, "timestamp": 1738935584, "checkpoint_dir_name": "checkpoint_000066", "should_checkpoint": true, "done": false, "training_iteration": 67, "trial_id": "e12c1511", "date": "2025-02-07_14-39-44", "time_this_iter_s": 1027.3727712631226, "time_total_s": 68960.26244235039, "pid": 52726, "hostname": "jan-desktop", "node_ip": "10.7.0.4", "config": {"learning_rate": 0.0001329291894316216, "batch_size": 4, "weight_decay": 4.2079886696066345e-06, "auto_cast": true, "max_epochs": 100}, "time_since_restore": 68960.26244235039, "iterations_since_restore": 67}
{"loss": 0.43874026735882377, "val_loss": 0.45683161980575987, "train_acc": 87.35722463634123, "val_acc": 86.84843811637082, "timestamp": 1738936613, "checkpoint_dir_name": "checkpoint_000067", "should_checkpoint": true, "done": false, "training_iteration": 68, "trial_id": "e12c1511", "date": "2025-02-07_14-56-53", "time_this_iter_s": 1028.9750680923462, "time_total_s": 69989.23751044273, "pid": 52726, "hostname": "jan-desktop", "node_ip": "10.7.0.4", "config": {"learning_rate": 0.0001329291894316216, "batch_size": 4, "weight_decay": 4.2079886696066345e-06, "auto_cast": true, "max_epochs": 100}, "time_since_restore": 69989.23751044273, "iterations_since_restore": 68}
{"loss": 0.4368230342316545, "val_loss": 0.46181557377179466, "train_acc": 87.50899151462853, "val_acc": 86.68397723537147, "timestamp": 1738937649, "checkpoint_dir_name": "checkpoint_000068", "should_checkpoint": true, "done": false, "training_iteration": 69, "trial_id": "e12c1511", "date": "2025-02-07_15-14-10", "time_this_iter_s": 1036.192806005478, "time_total_s": 71025.43031644821, "pid": 52726, "hostname": "jan-desktop", "node_ip": "10.7.0.4", "config": {"learning_rate": 0.0001329291894316216, "batch_size": 4, "weight_decay": 4.2079886696066345e-06, "auto_cast": true, "max_epochs": 100}, "time_since_restore": 71025.43031644821, "iterations_since_restore": 69}
{"loss": 0.4303701618174091, "val_loss": 0.45071252154393326, "train_acc": 87.66341751931296, "val_acc": 86.99923837113741, "timestamp": 1738938681, "checkpoint_dir_name": "checkpoint_000069", "should_checkpoint": true, "done": false, "training_iteration": 70, "trial_id": "e12c1511", "date": "2025-02-07_15-31-22", "time_this_iter_s": 1032.2497355937958, "time_total_s": 72057.68005204201, "pid": 52726, "hostname": "jan-desktop", "node_ip": "10.7.0.4", "config": {"learning_rate": 0.0001329291894316216, "batch_size": 4, "weight_decay": 4.2079886696066345e-06, "auto_cast": true, "max_epochs": 100}, "time_since_restore": 72057.68005204201, "iterations_since_restore": 70}
{"loss": 0.4365887706540525, "val_loss": 0.4751020799121923, "train_acc": 87.45407313239645, "val_acc": 86.66528034598949, "timestamp": 1738939708, "checkpoint_dir_name": "checkpoint_000070", "should_checkpoint": true, "done": false, "training_iteration": 71, "trial_id": "e12c1511", "date": "2025-02-07_15-48-28", "time_this_iter_s": 1026.1512434482574, "time_total_s": 73083.83129549026, "pid": 52726, "hostname": "jan-desktop", "node_ip": "10.7.0.4", "config": {"learning_rate": 0.0001329291894316216, "batch_size": 4, "weight_decay": 4.2079886696066345e-06, "auto_cast": true, "max_epochs": 100}, "time_since_restore": 73083.83129549026, "iterations_since_restore": 71}
{"loss": 0.4292147694378056, "val_loss": 0.4627636229308943, "train_acc": 87.681071586333, "val_acc": 86.77593102810651, "timestamp": 1738940738, "checkpoint_dir_name": "checkpoint_000071", "should_checkpoint": true, "done": false, "training_iteration": 72, "trial_id": "e12c1511", "date": "2025-02-07_16-05-39", "time_this_iter_s": 1030.4505734443665, "time_total_s": 74114.28186893463, "pid": 52726, "hostname": "jan-desktop", "node_ip": "10.7.0.4", "config": {"learning_rate": 0.0001329291894316216, "batch_size": 4, "weight_decay": 4.2079886696066345e-06, "auto_cast": true, "max_epochs": 100}, "time_since_restore": 74114.28186893463, "iterations_since_restore": 72}
{"loss": 0.4309712482797396, "val_loss": 0.4667910940841668, "train_acc": 87.53856611604208, "val_acc": 86.54030078895464, "timestamp": 1738941767, "checkpoint_dir_name": "checkpoint_000072", "should_checkpoint": true, "done": false, "training_iteration": 73, "trial_id": "e12c1511", "date": "2025-02-07_16-22-48", "time_this_iter_s": 1029.2268421649933, "time_total_s": 75143.50871109962, "pid": 52726, "hostname": "jan-desktop", "node_ip": "10.7.0.4", "config": {"learning_rate": 0.0001329291894316216, "batch_size": 4, "weight_decay": 4.2079886696066345e-06, "auto_cast": true, "max_epochs": 100}, "time_since_restore": 75143.50871109962, "iterations_since_restore": 73}
{"loss": 0.428870118767437, "val_loss": 0.46097996888682247, "train_acc": 87.65358355419954, "val_acc": 86.85582542324128, "timestamp": 1738942797, "checkpoint_dir_name": "checkpoint_000073", "should_checkpoint": true, "done": false, "training_iteration": 74, "trial_id": "e12c1511", "date": "2025-02-07_16-39-58", "time_this_iter_s": 1030.0353562831879, "time_total_s": 76173.54406738281, "pid": 52726, "hostname": "jan-desktop", "node_ip": "10.7.0.4", "config": {"learning_rate": 0.0001329291894316216, "batch_size": 4, "weight_decay": 4.2079886696066345e-06, "auto_cast": true, "max_epochs": 100}, "time_since_restore": 76173.54406738281, "iterations_since_restore": 74}
{"loss": 0.4287912345109766, "val_loss": 0.45853698187404207, "train_acc": 87.5534554517998, "val_acc": 86.83423395381328, "timestamp": 1738943822, "checkpoint_dir_name": "checkpoint_000074", "should_checkpoint": true, "done": false, "training_iteration": 75, "trial_id": "e12c1511", "date": "2025-02-07_16-57-03", "time_this_iter_s": 1024.7599954605103, "time_total_s": 77198.30406284332, "pid": 52726, "hostname": "jan-desktop", "node_ip": "10.7.0.4", "config": {"learning_rate": 0.0001329291894316216, "batch_size": 4, "weight_decay": 4.2079886696066345e-06, "auto_cast": true, "max_epochs": 100}, "time_since_restore": 77198.30406284332, "iterations_since_restore": 75}
{"loss": 0.4370112531880538, "val_loss": 0.4406430237698886, "train_acc": 87.51042991863905, "val_acc": 87.39699673323472, "timestamp": 1738944850, "checkpoint_dir_name": "checkpoint_000075", "should_checkpoint": true, "done": false, "training_iteration": 76, "trial_id": "e12c1511", "date": "2025-02-07_17-14-11", "time_this_iter_s": 1028.171947479248, "time_total_s": 78226.47601032257, "pid": 52726, "hostname": "jan-desktop", "node_ip": "10.7.0.4", "config": {"learning_rate": 0.0001329291894316216, "batch_size": 4, "weight_decay": 4.2079886696066345e-06, "auto_cast": true, "max_epochs": 100}, "time_since_restore": 78226.47601032257, "iterations_since_restore": 76}
{"loss": 0.4365231118397787, "val_loss": 0.4544836718361411, "train_acc": 87.50209432527942, "val_acc": 86.89120664858646, "timestamp": 1738945875, "checkpoint_dir_name": "checkpoint_000076", "should_checkpoint": true, "done": false, "training_iteration": 77, "trial_id": "e12c1511", "date": "2025-02-07_17-31-15", "time_this_iter_s": 1024.2613322734833, "time_total_s": 79250.73734259605, "pid": 52726, "hostname": "jan-desktop", "node_ip": "10.7.0.4", "config": {"learning_rate": 0.0001329291894316216, "batch_size": 4, "weight_decay": 4.2079886696066345e-06, "auto_cast": true, "max_epochs": 100}, "time_since_restore": 79250.73734259605, "iterations_since_restore": 77}
{"loss": 0.4341470108509788, "val_loss": 0.45034462690353394, "train_acc": 87.50428917036488, "val_acc": 86.90369956032215, "timestamp": 1738946898, "checkpoint_dir_name": "checkpoint_000077", "should_checkpoint": true, "done": false, "training_iteration": 78, "trial_id": "e12c1511", "date": "2025-02-07_17-48-19", "time_this_iter_s": 1023.3211934566498, "time_total_s": 80274.0585360527, "pid": 52726, "hostname": "jan-desktop", "node_ip": "10.7.0.4", "config": {"learning_rate": 0.0001329291894316216, "batch_size": 4, "weight_decay": 4.2079886696066345e-06, "auto_cast": true, "max_epochs": 100}, "time_since_restore": 80274.0585360527, "iterations_since_restore": 78}
{"loss": 0.4316490042033709, "val_loss": 0.4502899598247475, "train_acc": 87.53128962750658, "val_acc": 86.99841294789613, "timestamp": 1738947927, "checkpoint_dir_name": "checkpoint_000078", "should_checkpoint": true, "done": false, "training_iteration": 79, "trial_id": "e12c1511", "date": "2025-02-07_18-05-27", "time_this_iter_s": 1028.414211511612, "time_total_s": 81302.47274756432, "pid": 52726, "hostname": "jan-desktop", "node_ip": "10.7.0.4", "config": {"learning_rate": 0.0001329291894316216, "batch_size": 4, "weight_decay": 4.2079886696066345e-06, "auto_cast": true, "max_epochs": 100}, "time_since_restore": 81302.47274756432, "iterations_since_restore": 79}
{"loss": 0.4330692674426569, "val_loss": 0.4609768433775753, "train_acc": 87.4801778229783, "val_acc": 86.66874147353715, "timestamp": 1738948953, "checkpoint_dir_name": "checkpoint_000079", "should_checkpoint": true, "done": false, "training_iteration": 80, "trial_id": "e12c1511", "date": "2025-02-07_18-22-34", "time_this_iter_s": 1026.4870178699493, "time_total_s": 82328.95976543427, "pid": 52726, "hostname": "jan-desktop", "node_ip": "10.7.0.4", "config": {"learning_rate": 0.0001329291894316216, "batch_size": 4, "weight_decay": 4.2079886696066345e-06, "auto_cast": true, "max_epochs": 100}, "time_since_restore": 82328.95976543427, "iterations_since_restore": 80}
{"loss": 0.4308313778254928, "val_loss": 0.47373295427196555, "train_acc": 87.45269646819527, "val_acc": 86.54569485535832, "timestamp": 1738949979, "checkpoint_dir_name": "checkpoint_000080", "should_checkpoint": true, "done": false, "training_iteration": 81, "trial_id": "e12c1511", "date": "2025-02-07_18-39-40", "time_this_iter_s": 1025.89289188385, "time_total_s": 83354.85265731812, "pid": 52726, "hostname": "jan-desktop", "node_ip": "10.7.0.4", "config": {"learning_rate": 0.0001329291894316216, "batch_size": 4, "weight_decay": 4.2079886696066345e-06, "auto_cast": true, "max_epochs": 100}, "time_since_restore": 83354.85265731812, "iterations_since_restore": 81}
{"loss": 0.42839450812691615, "val_loss": 0.45877539024584824, "train_acc": 87.5923001674474, "val_acc": 86.80413646449703, "timestamp": 1738951007, "checkpoint_dir_name": "checkpoint_000081", "should_checkpoint": true, "done": false, "training_iteration": 82, "trial_id": "e12c1511", "date": "2025-02-07_18-56-47", "time_this_iter_s": 1027.4400777816772, "time_total_s": 84382.29273509979, "pid": 52726, "hostname": "jan-desktop", "node_ip": "10.7.0.4", "config": {"learning_rate": 0.0001329291894316216, "batch_size": 4, "weight_decay": 4.2079886696066345e-06, "auto_cast": true, "max_epochs": 100}, "time_since_restore": 84382.29273509979, "iterations_since_restore": 82}
{"loss": 0.4313883112070875, "val_loss": 0.4446130992058251, "train_acc": 87.56081620336127, "val_acc": 87.14855841140697, "timestamp": 1738952036, "checkpoint_dir_name": "checkpoint_000082", "should_checkpoint": true, "done": false, "training_iteration": 83, "trial_id": "e12c1511", "date": "2025-02-07_19-13-57", "time_this_iter_s": 1029.1427342891693, "time_total_s": 85411.43546938896, "pid": 52726, "hostname": "jan-desktop", "node_ip": "10.7.0.4", "config": {"learning_rate": 0.0001329291894316216, "batch_size": 4, "weight_decay": 4.2079886696066345e-06, "auto_cast": true, "max_epochs": 100}, "time_since_restore": 85411.43546938896, "iterations_since_restore": 83}
{"loss": 0.4253037228849199, "val_loss": 0.4596323792098297, "train_acc": 87.72054661817883, "val_acc": 86.7383727810651, "timestamp": 1738953089, "checkpoint_dir_name": "checkpoint_000083", "should_checkpoint": true, "done": false, "training_iteration": 84, "trial_id": "e12c1511", "date": "2025-02-07_19-31-29", "time_this_iter_s": 1052.6099190711975, "time_total_s": 86464.04538846016, "pid": 52726, "hostname": "jan-desktop", "node_ip": "10.7.0.4", "config": {"learning_rate": 0.0001329291894316216, "batch_size": 4, "weight_decay": 4.2079886696066345e-06, "auto_cast": true, "max_epochs": 100}, "time_since_restore": 86464.04538846016, "iterations_since_restore": 84}
{"loss": 0.4339308716677543, "val_loss": 0.4538902039080858, "train_acc": 87.51838580189842, "val_acc": 86.97510344756739, "timestamp": 1738954117, "checkpoint_dir_name": "checkpoint_000084", "should_checkpoint": true, "done": false, "training_iteration": 85, "trial_id": "e12c1511", "date": "2025-02-07_19-48-37", "time_this_iter_s": 1028.0210297107697, "time_total_s": 87492.06641817093, "pid": 52726, "hostname": "jan-desktop", "node_ip": "10.7.0.4", "config": {"learning_rate": 0.0001329291894316216, "batch_size": 4, "weight_decay": 4.2079886696066345e-06, "auto_cast": true, "max_epochs": 100}, "time_since_restore": 87492.06641817093, "iterations_since_restore": 85}
{"loss": 0.4317804056799246, "val_loss": 0.4473302141163084, "train_acc": 87.62224715955786, "val_acc": 87.07104372123602, "timestamp": 1738955142, "checkpoint_dir_name": "checkpoint_000085", "should_checkpoint": true, "done": false, "training_iteration": 86, "trial_id": "e12c1511", "date": "2025-02-07_20-05-42", "time_this_iter_s": 1024.967334985733, "time_total_s": 88517.03375315666, "pid": 52726, "hostname": "jan-desktop", "node_ip": "10.7.0.4", "config": {"learning_rate": 0.0001329291894316216, "batch_size": 4, "weight_decay": 4.2079886696066345e-06, "auto_cast": true, "max_epochs": 100}, "time_since_restore": 88517.03375315666, "iterations_since_restore": 86}
{"loss": 0.426300637311716, "val_loss": 0.45870001359118356, "train_acc": 87.69987110145463, "val_acc": 86.8021449704142, "timestamp": 1738956169, "checkpoint_dir_name": "checkpoint_000086", "should_checkpoint": true, "done": false, "training_iteration": 87, "trial_id": "e12c1511", "date": "2025-02-07_20-22-49", "time_this_iter_s": 1026.6389832496643, "time_total_s": 89543.67273640633, "pid": 52726, "hostname": "jan-desktop", "node_ip": "10.7.0.4", "config": {"learning_rate": 0.0001329291894316216, "batch_size": 4, "weight_decay": 4.2079886696066345e-06, "auto_cast": true, "max_epochs": 100}, "time_since_restore": 89543.67273640633, "iterations_since_restore": 87}
{"loss": 0.42663674049286376, "val_loss": 0.45561271189815467, "train_acc": 87.65911779359796, "val_acc": 86.94696149737015, "timestamp": 1738957196, "checkpoint_dir_name": "checkpoint_000087", "should_checkpoint": true, "done": false, "training_iteration": 88, "trial_id": "e12c1511", "date": "2025-02-07_20-39-57", "time_this_iter_s": 1027.605673789978, "time_total_s": 90571.2784101963, "pid": 52726, "hostname": "jan-desktop", "node_ip": "10.7.0.4", "config": {"learning_rate": 0.0001329291894316216, "batch_size": 4, "weight_decay": 4.2079886696066345e-06, "auto_cast": true, "max_epochs": 100}, "time_since_restore": 90571.2784101963, "iterations_since_restore": 88}
{"loss": 0.42733984674637515, "val_loss": 0.449365993084179, "train_acc": 87.70032703607824, "val_acc": 87.09862138395792, "timestamp": 1738958219, "checkpoint_dir_name": "checkpoint_000088", "should_checkpoint": true, "done": false, "training_iteration": 89, "trial_id": "e12c1511", "date": "2025-02-07_20-57-00", "time_this_iter_s": 1022.9038486480713, "time_total_s": 91594.18225884438, "pid": 52726, "hostname": "jan-desktop", "node_ip": "10.7.0.4", "config": {"learning_rate": 0.0001329291894316216, "batch_size": 4, "weight_decay": 4.2079886696066345e-06, "auto_cast": true, "max_epochs": 100}, "time_since_restore": 91594.18225884438, "iterations_since_restore": 89}
{"loss": 0.42135790782463217, "val_loss": 0.4555029801693228, "train_acc": 87.85511212812294, "val_acc": 86.86476454635108, "timestamp": 1738959252, "checkpoint_dir_name": "checkpoint_000089", "should_checkpoint": true, "done": false, "training_iteration": 90, "trial_id": "e12c1511", "date": "2025-02-07_21-14-12", "time_this_iter_s": 1032.2196264266968, "time_total_s": 92626.40188527107, "pid": 52726, "hostname": "jan-desktop", "node_ip": "10.7.0.4", "config": {"learning_rate": 0.0001329291894316216, "batch_size": 4, "weight_decay": 4.2079886696066345e-06, "auto_cast": true, "max_epochs": 100}, "time_since_restore": 92626.40188527107, "iterations_since_restore": 90}
{"loss": 0.42475207328460074, "val_loss": 0.451268674749881, "train_acc": 87.74842037002794, "val_acc": 86.84234539365549, "timestamp": 1738960287, "checkpoint_dir_name": "checkpoint_000090", "should_checkpoint": true, "done": false, "training_iteration": 91, "trial_id": "e12c1511", "date": "2025-02-07_21-31-28", "time_this_iter_s": 1035.3605892658234, "time_total_s": 93661.7624745369, "pid": 52726, "hostname": "jan-desktop", "node_ip": "10.7.0.4", "config": {"learning_rate": 0.0001329291894316216, "batch_size": 4, "weight_decay": 4.2079886696066345e-06, "auto_cast": true, "max_epochs": 100}, "time_since_restore": 93661.7624745369, "iterations_since_restore": 91}
{"loss": 0.4274940961237169, "val_loss": 0.45202923962225516, "train_acc": 87.60184631307528, "val_acc": 87.16122976249179, "timestamp": 1738961318, "checkpoint_dir_name": "checkpoint_000091", "should_checkpoint": true, "done": false, "training_iteration": 92, "trial_id": "e12c1511", "date": "2025-02-07_21-48-38", "time_this_iter_s": 1030.503727197647, "time_total_s": 94692.26620173454, "pid": 52726, "hostname": "jan-desktop", "node_ip": "10.7.0.4", "config": {"learning_rate": 0.0001329291894316216, "batch_size": 4, "weight_decay": 4.2079886696066345e-06, "auto_cast": true, "max_epochs": 100}, "time_since_restore": 94692.26620173454, "iterations_since_restore": 92}
{"loss": 0.4226714217564505, "val_loss": 0.44563758810361226, "train_acc": 87.78255049104207, "val_acc": 87.26688640285997, "timestamp": 1738962345, "checkpoint_dir_name": "checkpoint_000092", "should_checkpoint": true, "done": false, "training_iteration": 93, "trial_id": "e12c1511", "date": "2025-02-07_22-05-46", "time_this_iter_s": 1027.394017457962, "time_total_s": 95719.6602191925, "pid": 52726, "hostname": "jan-desktop", "node_ip": "10.7.0.4", "config": {"learning_rate": 0.0001329291894316216, "batch_size": 4, "weight_decay": 4.2079886696066345e-06, "auto_cast": true, "max_epochs": 100}, "time_since_restore": 95719.6602191925, "iterations_since_restore": 93}
{"loss": 0.42847994284393887, "val_loss": 0.459696741633945, "train_acc": 87.64205510868672, "val_acc": 86.90626171104536, "timestamp": 1738963370, "checkpoint_dir_name": "checkpoint_000093", "should_checkpoint": true, "done": false, "training_iteration": 94, "trial_id": "e12c1511", "date": "2025-02-07_22-22-51", "time_this_iter_s": 1025.3541116714478, "time_total_s": 96745.01433086395, "pid": 52726, "hostname": "jan-desktop", "node_ip": "10.7.0.4", "config": {"learning_rate": 0.0001329291894316216, "batch_size": 4, "weight_decay": 4.2079886696066345e-06, "auto_cast": true, "max_epochs": 100}, "time_since_restore": 96745.01433086395, "iterations_since_restore": 94}
{"loss": 0.4235835081106052, "val_loss": 0.45062343857354586, "train_acc": 87.7619348650148, "val_acc": 87.02622996794872, "timestamp": 1738964466, "checkpoint_dir_name": "checkpoint_000094", "should_checkpoint": true, "done": false, "training_iteration": 95, "trial_id": "e12c1511", "date": "2025-02-07_22-41-06", "time_this_iter_s": 1095.280733346939, "time_total_s": 97840.29506421089, "pid": 52726, "hostname": "jan-desktop", "node_ip": "10.7.0.4", "config": {"learning_rate": 0.0001329291894316216, "batch_size": 4, "weight_decay": 4.2079886696066345e-06, "auto_cast": true, "max_epochs": 100}, "time_since_restore": 97840.29506421089, "iterations_since_restore": 95}
{"loss": 0.42449733880762425, "val_loss": 0.4499996577017009, "train_acc": 87.79141970742933, "val_acc": 87.04111614480605, "timestamp": 1738965494, "checkpoint_dir_name": "checkpoint_000095", "should_checkpoint": true, "done": false, "training_iteration": 96, "trial_id": "e12c1511", "date": "2025-02-07_22-58-15", "time_this_iter_s": 1028.2659237384796, "time_total_s": 98868.56098794937, "pid": 52726, "hostname": "jan-desktop", "node_ip": "10.7.0.4", "config": {"learning_rate": 0.0001329291894316216, "batch_size": 4, "weight_decay": 4.2079886696066345e-06, "auto_cast": true, "max_epochs": 100}, "time_since_restore": 98868.56098794937, "iterations_since_restore": 96}
{"loss": 0.4309200148056779, "val_loss": 0.468883802883534, "train_acc": 87.59563861152202, "val_acc": 86.56638960798817, "timestamp": 1738966524, "checkpoint_dir_name": "checkpoint_000096", "should_checkpoint": true, "done": false, "training_iteration": 97, "trial_id": "e12c1511", "date": "2025-02-07_23-15-25", "time_this_iter_s": 1029.9434716701508, "time_total_s": 99898.50445961952, "pid": 52726, "hostname": "jan-desktop", "node_ip": "10.7.0.4", "config": {"learning_rate": 0.0001329291894316216, "batch_size": 4, "weight_decay": 4.2079886696066345e-06, "auto_cast": true, "max_epochs": 100}, "time_since_restore": 99898.50445961952, "iterations_since_restore": 97}
{"loss": 0.4207977851283633, "val_loss": 0.46270802963111135, "train_acc": 87.82417701655983, "val_acc": 86.9210863535503, "timestamp": 1738967553, "checkpoint_dir_name": "checkpoint_000097", "should_checkpoint": true, "done": false, "training_iteration": 98, "trial_id": "e12c1511", "date": "2025-02-07_23-32-33", "time_this_iter_s": 1028.6015975475311, "time_total_s": 100927.10605716705, "pid": 52726, "hostname": "jan-desktop", "node_ip": "10.7.0.4", "config": {"learning_rate": 0.0001329291894316216, "batch_size": 4, "weight_decay": 4.2079886696066345e-06, "auto_cast": true, "max_epochs": 100}, "time_since_restore": 100927.10605716705, "iterations_since_restore": 98}
{"loss": 0.4267255674499191, "val_loss": 0.4596321351784799, "train_acc": 87.73082036386424, "val_acc": 86.6782803254438, "timestamp": 1738968579, "checkpoint_dir_name": "checkpoint_000098", "should_checkpoint": true, "done": false, "training_iteration": 99, "trial_id": "e12c1511", "date": "2025-02-07_23-49-40", "time_this_iter_s": 1026.481620311737, "time_total_s": 101953.58767747879, "pid": 52726, "hostname": "jan-desktop", "node_ip": "10.7.0.4", "config": {"learning_rate": 0.0001329291894316216, "batch_size": 4, "weight_decay": 4.2079886696066345e-06, "auto_cast": true, "max_epochs": 100}, "time_since_restore": 101953.58767747879, "iterations_since_restore": 99}
{"loss": 0.4265241950796917, "val_loss": 0.43929264807763196, "train_acc": 87.69623679939184, "val_acc": 87.35873202251808, "timestamp": 1738969606, "checkpoint_dir_name": "checkpoint_000099", "should_checkpoint": true, "done": true, "training_iteration": 100, "trial_id": "e12c1511", "date": "2025-02-08_00-06-46", "time_this_iter_s": 1026.2671856880188, "time_total_s": 102979.85486316681, "pid": 52726, "hostname": "jan-desktop", "node_ip": "10.7.0.4", "config": {"learning_rate": 0.0001329291894316216, "batch_size": 4, "weight_decay": 4.2079886696066345e-06, "auto_cast": true, "max_epochs": 100}, "time_since_restore": 102979.85486316681, "iterations_since_restore": 100}
