{"loss": 0.9070784239460239, "val_loss": 0.615386278288705, "train_acc": 75.97320749169894, "val_acc": 82.59206118832745, "timestamp": 1737421079, "checkpoint_dir_name": "checkpoint_000000", "should_checkpoint": true, "done": false, "training_iteration": 1, "trial_id": "aca39994", "date": "2025-01-21_01-58-00", "time_this_iter_s": 92.13901329040527, "time_total_s": 92.13901329040527, "pid": 727178, "hostname": "jan-desktop", "node_ip": "10.7.0.4", "config": {"learning_rate": 2.1352499884666333e-05, "batch_size": 8, "weight_decay": 3.747768893884739e-05, "auto_cast": true, "max_epochs": 100}, "time_since_restore": 92.13901329040527, "iterations_since_restore": 1}
{"loss": 0.6343303055857583, "val_loss": 0.5347411632537842, "train_acc": 81.45715430244562, "val_acc": 83.79815873632455, "timestamp": 1737421167, "checkpoint_dir_name": "checkpoint_000001", "should_checkpoint": true, "done": false, "training_iteration": 2, "trial_id": "aca39994", "date": "2025-01-21_01-59-27", "time_this_iter_s": 87.26716041564941, "time_total_s": 179.4061737060547, "pid": 727178, "hostname": "jan-desktop", "node_ip": "10.7.0.4", "config": {"learning_rate": 2.1352499884666333e-05, "batch_size": 8, "weight_decay": 3.747768893884739e-05, "auto_cast": true, "max_epochs": 100}, "time_since_restore": 179.4061737060547, "iterations_since_restore": 2}
{"loss": 0.5524375456914628, "val_loss": 0.48788542662348067, "train_acc": 83.34551413972372, "val_acc": 84.95441139691796, "timestamp": 1737421255, "checkpoint_dir_name": "checkpoint_000002", "should_checkpoint": true, "done": false, "training_iteration": 3, "trial_id": "aca39994", "date": "2025-01-21_02-00-56", "time_this_iter_s": 88.61386775970459, "time_total_s": 268.0200414657593, "pid": 727178, "hostname": "jan-desktop", "node_ip": "10.7.0.4", "config": {"learning_rate": 2.1352499884666333e-05, "batch_size": 8, "weight_decay": 3.747768893884739e-05, "auto_cast": true, "max_epochs": 100}, "time_since_restore": 268.0200414657593, "iterations_since_restore": 3}
{"loss": 0.5232494765048404, "val_loss": 0.46134330332279205, "train_acc": 84.19319217333233, "val_acc": 85.74548031692989, "timestamp": 1737421343, "checkpoint_dir_name": "checkpoint_000003", "should_checkpoint": true, "done": false, "training_iteration": 4, "trial_id": "aca39994", "date": "2025-01-21_02-02-23", "time_this_iter_s": 87.53626990318298, "time_total_s": 355.55631136894226, "pid": 727178, "hostname": "jan-desktop", "node_ip": "10.7.0.4", "config": {"learning_rate": 2.1352499884666333e-05, "batch_size": 8, "weight_decay": 3.747768893884739e-05, "auto_cast": true, "max_epochs": 100}, "time_since_restore": 355.55631136894226, "iterations_since_restore": 4}
{"loss": 0.48522229964355773, "val_loss": 0.4523541637829372, "train_acc": 85.01246853848282, "val_acc": 85.96923688859563, "timestamp": 1737421430, "checkpoint_dir_name": "checkpoint_000004", "should_checkpoint": true, "done": true, "training_iteration": 5, "trial_id": "aca39994", "date": "2025-01-21_02-03-51", "time_this_iter_s": 87.50003862380981, "time_total_s": 443.0563499927521, "pid": 727178, "hostname": "jan-desktop", "node_ip": "10.7.0.4", "config": {"learning_rate": 2.1352499884666333e-05, "batch_size": 8, "weight_decay": 3.747768893884739e-05, "auto_cast": true, "max_epochs": 100}, "time_since_restore": 443.0563499927521, "iterations_since_restore": 5}
