{"loss": 0.8016431382019743, "val_loss": 0.6389381366667988, "train_acc": 76.91655514345919, "val_acc": 80.98324624324209, "timestamp": 1737597141, "checkpoint_dir_name": "checkpoint_000000", "should_checkpoint": true, "done": false, "training_iteration": 1, "trial_id": "bc88a6d4", "date": "2025-01-23_02-52-22", "time_this_iter_s": 137.35096192359924, "time_total_s": 137.35096192359924, "pid": 913481, "hostname": "jan-desktop", "node_ip": "10.7.0.4", "config": {"learning_rate": 0.00017528114829507303, "batch_size": 4, "weight_decay": 0.001292232395380401, "auto_cast": true, "max_epochs": 100}, "time_since_restore": 137.35096192359924, "iterations_since_restore": 1}
{"loss": 0.6739357304122808, "val_loss": 0.6454333600809248, "train_acc": 80.16290813503043, "val_acc": 81.03166571772168, "timestamp": 1737597275, "checkpoint_dir_name": "checkpoint_000001", "should_checkpoint": true, "done": false, "training_iteration": 2, "trial_id": "bc88a6d4", "date": "2025-01-23_02-54-35", "time_this_iter_s": 133.81626796722412, "time_total_s": 271.16722989082336, "pid": 913481, "hostname": "jan-desktop", "node_ip": "10.7.0.4", "config": {"learning_rate": 0.00017528114829507303, "batch_size": 4, "weight_decay": 0.001292232395380401, "auto_cast": true, "max_epochs": 100}, "time_since_restore": 271.16722989082336, "iterations_since_restore": 2}
{"loss": 0.6334046321860749, "val_loss": 0.5904342019729477, "train_acc": 81.37453556016133, "val_acc": 82.06748595206675, "timestamp": 1737597409, "checkpoint_dir_name": "checkpoint_000002", "should_checkpoint": true, "done": false, "training_iteration": 3, "trial_id": "bc88a6d4", "date": "2025-01-23_02-56-49", "time_this_iter_s": 133.84264063835144, "time_total_s": 405.0098705291748, "pid": 913481, "hostname": "jan-desktop", "node_ip": "10.7.0.4", "config": {"learning_rate": 0.00017528114829507303, "batch_size": 4, "weight_decay": 0.001292232395380401, "auto_cast": true, "max_epochs": 100}, "time_since_restore": 405.0098705291748, "iterations_since_restore": 3}
{"loss": 0.6136655558785089, "val_loss": 0.5416762603701447, "train_acc": 81.83384361297944, "val_acc": 83.70143818377251, "timestamp": 1737597542, "checkpoint_dir_name": "checkpoint_000003", "should_checkpoint": true, "done": false, "training_iteration": 4, "trial_id": "bc88a6d4", "date": "2025-01-23_02-59-03", "time_this_iter_s": 133.92592930793762, "time_total_s": 538.9357998371124, "pid": 913481, "hostname": "jan-desktop", "node_ip": "10.7.0.4", "config": {"learning_rate": 0.00017528114829507303, "batch_size": 4, "weight_decay": 0.001292232395380401, "auto_cast": true, "max_epochs": 100}, "time_since_restore": 538.9357998371124, "iterations_since_restore": 4}
{"loss": 0.582124922183349, "val_loss": 0.5363830227217228, "train_acc": 82.66515101528245, "val_acc": 83.99274123600527, "timestamp": 1737597679, "checkpoint_dir_name": "checkpoint_000004", "should_checkpoint": true, "done": true, "training_iteration": 5, "trial_id": "bc88a6d4", "date": "2025-01-23_03-01-20", "time_this_iter_s": 136.40045356750488, "time_total_s": 675.3362534046173, "pid": 913481, "hostname": "jan-desktop", "node_ip": "10.7.0.4", "config": {"learning_rate": 0.00017528114829507303, "batch_size": 4, "weight_decay": 0.001292232395380401, "auto_cast": true, "max_epochs": 100}, "time_since_restore": 675.3362534046173, "iterations_since_restore": 5}
