{"loss": 1.6206431989189531, "val_loss": 1.0437859858785357, "train_acc": 65.93690169905496, "val_acc": 78.87862372823635, "timestamp": 1736967499, "checkpoint_dir_name": "checkpoint_000000", "should_checkpoint": true, "done": false, "training_iteration": 1, "trial_id": "c5a3170b", "date": "2025-01-15_19-58-20", "time_this_iter_s": 112.91344332695007, "time_total_s": 112.91344332695007, "pid": 138971, "hostname": "jan-desktop", "node_ip": "10.7.0.4", "config": {"learning_rate": 1.837499987326739e-05, "batch_size": 16, "weight_decay": 0.001450005656162197, "auto_cast": true, "max_epochs": 100}, "time_since_restore": 112.91344332695007, "iterations_since_restore": 1}
{"loss": 0.963265527066567, "val_loss": 0.8184241890907288, "train_acc": 79.50103097994977, "val_acc": 81.93236372440509, "timestamp": 1736967612, "checkpoint_dir_name": "checkpoint_000001", "should_checkpoint": true, "done": false, "training_iteration": 2, "trial_id": "c5a3170b", "date": "2025-01-15_20-00-13", "time_this_iter_s": 113.61711168289185, "time_total_s": 226.53055500984192, "pid": 138971, "hostname": "jan-desktop", "node_ip": "10.7.0.4", "config": {"learning_rate": 1.837499987326739e-05, "batch_size": 16, "weight_decay": 0.001450005656162197, "auto_cast": true, "max_epochs": 100}, "time_since_restore": 226.53055500984192, "iterations_since_restore": 2}
{"loss": 0.8090745137749816, "val_loss": 0.7254919001034328, "train_acc": 81.6583344086565, "val_acc": 82.97514540143034, "timestamp": 1736967724, "checkpoint_dir_name": "checkpoint_000002", "should_checkpoint": true, "done": false, "training_iteration": 3, "trial_id": "c5a3170b", "date": "2025-01-15_20-02-04", "time_this_iter_s": 110.88934063911438, "time_total_s": 337.4198956489563, "pid": 138971, "hostname": "jan-desktop", "node_ip": "10.7.0.4", "config": {"learning_rate": 1.837499987326739e-05, "batch_size": 16, "weight_decay": 0.001450005656162197, "auto_cast": true, "max_epochs": 100}, "time_since_restore": 337.4198956489563, "iterations_since_restore": 3}
{"loss": 0.7186893198987563, "val_loss": 0.6442804404667446, "train_acc": 83.04734409587715, "val_acc": 84.43253932357072, "timestamp": 1736967835, "checkpoint_dir_name": "checkpoint_000003", "should_checkpoint": true, "done": false, "training_iteration": 4, "trial_id": "c5a3170b", "date": "2025-01-15_20-03-56", "time_this_iter_s": 111.33696627616882, "time_total_s": 448.7568619251251, "pid": 138971, "hostname": "jan-desktop", "node_ip": "10.7.0.4", "config": {"learning_rate": 1.837499987326739e-05, "batch_size": 16, "weight_decay": 0.001450005656162197, "auto_cast": true, "max_epochs": 100}, "time_since_restore": 448.7568619251251, "iterations_since_restore": 4}
{"loss": 0.6661789828924825, "val_loss": 0.6039859984602247, "train_acc": 83.65162405948023, "val_acc": 84.67591710655145, "timestamp": 1736967946, "checkpoint_dir_name": "checkpoint_000004", "should_checkpoint": true, "done": true, "training_iteration": 5, "trial_id": "c5a3170b", "date": "2025-01-15_20-05-46", "time_this_iter_s": 110.65721940994263, "time_total_s": 559.4140813350677, "pid": 138971, "hostname": "jan-desktop", "node_ip": "10.7.0.4", "config": {"learning_rate": 1.837499987326739e-05, "batch_size": 16, "weight_decay": 0.001450005656162197, "auto_cast": true, "max_epochs": 100}, "time_since_restore": 559.4140813350677, "iterations_since_restore": 5}
